kealutils/AppErr.py
kealutils/CONST.py
kealutils/__init__.py
kealutils/dbmgr.py
kealutils/logger.py
kealutils/utils.py
kealutils/test/module_tester.py
kealutils-0.20230328.1812.dist-info/METADATA
kealutils-0.20230328.1812.dist-info/WHEEL
kealutils-0.20230328.1812.dist-info/top_level.txt
kealutils-0.20230328.1812.dist-info/RECORD
