Metadata-Version: 2.1
Name: kealutils
Version: 0.20230328.1812
Summary: Some utils for me.
Author: realizer
Author-email: bonfireof@gmail.com
Classifier: Programming Language :: Python :: 3
Classifier: License :: OSI Approved :: Apache Software License
Classifier: Operating System :: OS Independent
Requires-Python: >=3.1
